{
 "positive": [
  {
   "name": "Annotation 0",
   "vertices": [
    [
     11349,
     6475
    ],
    [
     11390,
     6328
    ],
    [
     11443,
     6222
    ],
    [
     11590,
     6197
    ],
    [
     11721,
     6157
    ],
    [
     11782,
     6087
    ],
    [
     11921,
     5977
    ],
    [
     12052,
     5895
    ],
    [
     12166,
     5797
    ],
    [
     12272,
     5638
    ],
    [
     12317,
     5572
    ],
    [
     12431,
     5662
    ],
    [
     12476,
     5760
    ],
    [
     12554,
     5715
    ],
    [
     12558,
     5609
    ],
    [
     12525,
     5519
    ],
    [
     12701,
     5536
    ],
    [
     12865,
     5568
    ],
    [
     12881,
     5540
    ],
    [
     12685,
     5454
    ],
    [
     12652,
     5282
    ],
    [
     12750,
     5213
    ],
    [
     12914,
     5217
    ],
    [
     13085,
     5209
    ],
    [
     13257,
     5037
    ],
    [
     13236,
     4939
    ],
    [
     13334,
     4894
    ],
    [
     13502,
     4853
    ],
    [
     13657,
     4792
    ],
    [
     13731,
     4714
    ],
    [
     13882,
     4739
    ],
    [
     14033,
     4804
    ],
    [
     14049,
     4817
    ],
    [
     14062,
     4898
    ],
    [
     13988,
     4960
    ],
    [
     13747,
     4976
    ],
    [
     13751,
     5025
    ],
    [
     13927,
     5062
    ],
    [
     14086,
     5127
    ],
    [
     14229,
     5209
    ],
    [
     14331,
     5339
    ],
    [
     14278,
     5495
    ],
    [
     14176,
     5499
    ],
    [
     13731,
     5421
    ],
    [
     13678,
     5438
    ],
    [
     13702,
     5507
    ],
    [
     13837,
     5605
    ],
    [
     13923,
     5699
    ],
    [
     14057,
     5801
    ],
    [
     14078,
     5875
    ],
    [
     13923,
     5997
    ],
    [
     13816,
     6083
    ],
    [
     13735,
     6095
    ],
    [
     13698,
     6022
    ],
    [
     13661,
     5862
    ],
    [
     13559,
     5756
    ],
    [
     13445,
     5719
    ],
    [
     13298,
     5744
    ],
    [
     13347,
     5797
    ],
    [
     13412,
     5883
    ],
    [
     13543,
     5985
    ],
    [
     13620,
     6079
    ],
    [
     13624,
     6148
    ],
    [
     13575,
     6177
    ],
    [
     13432,
     6189
    ],
    [
     13326,
     6218
    ],
    [
     13293,
     6381
    ],
    [
     13159,
     6483
    ],
    [
     12991,
     6483
    ],
    [
     12877,
     6442
    ],
    [
     12852,
     6369
    ],
    [
     12930,
     6197
    ],
    [
     12967,
     5924
    ],
    [
     12901,
     5736
    ],
    [
     12754,
     5711
    ],
    [
     12693,
     5756
    ],
    [
     12660,
     5850
    ],
    [
     12664,
     6018
    ],
    [
     12701,
     6103
    ],
    [
     12734,
     6197
    ],
    [
     12766,
     6361
    ],
    [
     12771,
     6471
    ],
    [
     12750,
     6545
    ],
    [
     12583,
     6598
    ],
    [
     12476,
     6610
    ],
    [
     12313,
     6639
    ],
    [
     12146,
     6647
    ],
    [
     11982,
     6667
    ],
    [
     11811,
     6684
    ],
    [
     11639,
     6679
    ],
    [
     11459,
     6659
    ],
    [
     11402,
     6569
    ]
   ]
  },
  {
   "name": "Annotation 1",
   "vertices": [
    [
     15600,
     5552
    ],
    [
     15649,
     5457
    ],
    [
     15674,
     5396
    ],
    [
     15661,
     5316
    ],
    [
     15689,
     5237
    ],
    [
     15839,
     5163
    ],
    [
     15992,
     5090
    ],
    [
     16163,
     5023
    ],
    [
     16187,
     5121
    ],
    [
     16178,
     5173
    ],
    [
     16288,
     5124
    ],
    [
     16340,
     5173
    ],
    [
     16432,
     5179
    ],
    [
     16515,
     5182
    ],
    [
     16573,
     5197
    ],
    [
     16784,
     5225
    ],
    [
     16870,
     5212
    ],
    [
     16958,
     5206
    ],
    [
     17032,
     5218
    ],
    [
     17068,
     5273
    ],
    [
     17087,
     5341
    ],
    [
     17249,
     5402
    ],
    [
     17356,
     5399
    ],
    [
     17405,
     5512
    ],
    [
     17350,
     5622
    ],
    [
     17237,
     5671
    ],
    [
     17114,
     5653
    ],
    [
     16986,
     5607
    ],
    [
     16928,
     5543
    ],
    [
     16848,
     5555
    ],
    [
     16790,
     5616
    ],
    [
     16701,
     5665
    ],
    [
     16585,
     5683
    ],
    [
     16466,
     5674
    ],
    [
     16359,
     5735
    ],
    [
     16313,
     5735
    ],
    [
     16191,
     5726
    ],
    [
     16117,
     5671
    ],
    [
     16080,
     5549
    ],
    [
     16059,
     5500
    ],
    [
     15995,
     5399
    ],
    [
     15967,
     5286
    ],
    [
     15940,
     5270
    ],
    [
     15842,
     5310
    ],
    [
     15869,
     5368
    ],
    [
     15891,
     5460
    ],
    [
     15882,
     5549
    ],
    [
     15875,
     5579
    ],
    [
     15756,
     5607
    ],
    [
     15729,
     5613
    ],
    [
     15661,
     5589
    ]
   ]
  },
  {
   "name": "Annotation 2",
   "vertices": [
    [
     10044,
     5915
    ],
    [
     10144,
     5899
    ],
    [
     10239,
     5885
    ],
    [
     10317,
     5894
    ],
    [
     10395,
     5896
    ],
    [
     10450,
     5923
    ],
    [
     10528,
     6002
    ],
    [
     10566,
     6104
    ],
    [
     10555,
     6212
    ],
    [
     10560,
     6323
    ],
    [
     10558,
     6434
    ],
    [
     10560,
     6547
    ],
    [
     10628,
     6637
    ],
    [
     10695,
     6723
    ],
    [
     10704,
     6834
    ],
    [
     10679,
     6939
    ],
    [
     10628,
     6964
    ],
    [
     10509,
     6896
    ],
    [
     10420,
     6874
    ],
    [
     10363,
     6815
    ],
    [
     10363,
     6780
    ],
    [
     10420,
     6742
    ],
    [
     10420,
     6704
    ],
    [
     10368,
     6672
    ],
    [
     10331,
     6647
    ],
    [
     10320,
     6607
    ],
    [
     10314,
     6572
    ],
    [
     10255,
     6488
    ],
    [
     10271,
     6404
    ],
    [
     10250,
     6307
    ],
    [
     10225,
     6275
    ],
    [
     10171,
     6258
    ],
    [
     10093,
     6210
    ],
    [
     10079,
     6158
    ],
    [
     10082,
     6121
    ],
    [
     10106,
     6104
    ],
    [
     10141,
     6075
    ],
    [
     10185,
     6023
    ],
    [
     10171,
     5980
    ],
    [
     10082,
     5991
    ],
    [
     10058,
     5980
    ],
    [
     10033,
     5956
    ]
   ]
  }
 ],
 "negative": []
}