{
 "positive": [
  {
   "name": "Annotation 0",
   "vertices": [
    [
     5412,
     19963
    ],
    [
     5635,
     19876
    ],
    [
     5725,
     19815
    ],
    [
     5789,
     19747
    ],
    [
     5838,
     19708
    ],
    [
     5828,
     19628
    ],
    [
     5889,
     19579
    ],
    [
     6009,
     19586
    ],
    [
     6105,
     19615
    ],
    [
     6186,
     19628
    ],
    [
     6225,
     19608
    ],
    [
     6270,
     19508
    ],
    [
     6363,
     19425
    ],
    [
     6502,
     19405
    ],
    [
     6550,
     19405
    ],
    [
     6656,
     19499
    ],
    [
     6660,
     19602
    ],
    [
     6586,
     19682
    ],
    [
     6440,
     19734
    ],
    [
     6273,
     19770
    ],
    [
     6205,
     19792
    ],
    [
     6283,
     19815
    ],
    [
     6353,
     19860
    ],
    [
     6363,
     19937
    ],
    [
     6334,
     20063
    ],
    [
     6324,
     20108
    ],
    [
     6225,
     20263
    ],
    [
     6192,
     20311
    ],
    [
     6163,
     20356
    ],
    [
     6237,
     20437
    ],
    [
     6208,
     20579
    ],
    [
     6147,
     20624
    ],
    [
     6060,
     20569
    ],
    [
     5954,
     20508
    ],
    [
     5918,
     20492
    ],
    [
     5854,
     20524
    ],
    [
     5838,
     20579
    ],
    [
     5799,
     20679
    ],
    [
     5760,
     20650
    ],
    [
     5741,
     20592
    ],
    [
     5770,
     20466
    ],
    [
     5696,
     20562
    ],
    [
     5531,
     20601
    ],
    [
     5448,
     20608
    ],
    [
     5506,
     20492
    ],
    [
     5593,
     20340
    ],
    [
     5635,
     20305
    ],
    [
     5706,
     20301
    ],
    [
     5822,
     20272
    ],
    [
     5854,
     20227
    ],
    [
     5770,
     20227
    ],
    [
     5660,
     20218
    ],
    [
     5619,
     20198
    ],
    [
     5619,
     20153
    ],
    [
     5644,
     20073
    ],
    [
     5628,
     20134
    ],
    [
     5496,
     20137
    ],
    [
     5457,
     20111
    ],
    [
     5422,
     20076
    ]
   ]
  },
  {
   "name": "Annotation 1",
   "vertices": [
    [
     6848,
     18193
    ],
    [
     6784,
     18173
    ],
    [
     6808,
     18119
    ],
    [
     6868,
     18055
    ],
    [
     6940,
     18039
    ],
    [
     6996,
     18065
    ],
    [
     7058,
     18096
    ],
    [
     7108,
     18107
    ],
    [
     7182,
     18134
    ],
    [
     7245,
     18151
    ],
    [
     7282,
     18156
    ],
    [
     7285,
     18139
    ],
    [
     7219,
     18118
    ],
    [
     7115,
     18077
    ],
    [
     7043,
     18030
    ],
    [
     6984,
     17983
    ],
    [
     6971,
     17926
    ],
    [
     7006,
     17886
    ],
    [
     7112,
     17912
    ],
    [
     7193,
     17941
    ],
    [
     7263,
     17988
    ],
    [
     7319,
     18059
    ],
    [
     7347,
     18099
    ],
    [
     7383,
     18144
    ],
    [
     7480,
     18155
    ],
    [
     7495,
     18180
    ],
    [
     7485,
     18250
    ],
    [
     7453,
     18284
    ],
    [
     7399,
     18314
    ],
    [
     7364,
     18331
    ],
    [
     7293,
     18309
    ],
    [
     7241,
     18304
    ],
    [
     7221,
     18311
    ],
    [
     7208,
     18340
    ],
    [
     7144,
     18363
    ],
    [
     7105,
     18365
    ],
    [
     7058,
     18336
    ],
    [
     6986,
     18276
    ],
    [
     6930,
     18237
    ],
    [
     6893,
     18218
    ]
   ]
  },
  {
   "name": "Annotation 2",
   "vertices": [
    [
     9528,
     13305
    ],
    [
     9605,
     13233
    ],
    [
     9612,
     13154
    ],
    [
     9668,
     13120
    ],
    [
     9720,
     13072
    ],
    [
     9795,
     13012
    ],
    [
     9840,
     12969
    ],
    [
     9845,
     12955
    ],
    [
     9780,
     12950
    ],
    [
     9716,
     12952
    ],
    [
     9668,
     12940
    ],
    [
     9687,
     12897
    ],
    [
     9739,
     12866
    ],
    [
     9778,
     12794
    ],
    [
     9797,
     12751
    ],
    [
     9828,
     12708
    ],
    [
     9864,
     12684
    ],
    [
     9931,
     12636
    ],
    [
     10013,
     12607
    ],
    [
     10073,
     12610
    ],
    [
     10104,
     12657
    ],
    [
     10118,
     12720
    ],
    [
     10092,
     12811
    ],
    [
     10068,
     12840
    ],
    [
     10044,
     12840
    ],
    [
     10032,
     12888
    ],
    [
     10056,
     12933
    ],
    [
     10068,
     12952
    ],
    [
     10109,
     12943
    ],
    [
     10169,
     12933
    ],
    [
     10233,
     12924
    ],
    [
     10277,
     12924
    ],
    [
     10346,
     12962
    ],
    [
     10348,
     13020
    ],
    [
     10269,
     13041
    ],
    [
     10277,
     13065
    ],
    [
     10305,
     13101
    ],
    [
     10337,
     13123
    ],
    [
     10351,
     13166
    ],
    [
     10305,
     13185
    ],
    [
     10233,
     13185
    ],
    [
     10176,
     13173
    ],
    [
     10135,
     13171
    ],
    [
     10085,
     13147
    ],
    [
     10109,
     13173
    ],
    [
     10130,
     13221
    ],
    [
     10133,
     13267
    ],
    [
     10082,
     13307
    ],
    [
     10058,
     13310
    ],
    [
     10042,
     13264
    ],
    [
     9974,
     13168
    ],
    [
     9912,
     13135
    ],
    [
     9893,
     13089
    ],
    [
     9895,
     13022
    ],
    [
     9874,
     13048
    ],
    [
     9852,
     13099
    ],
    [
     9778,
     13199
    ],
    [
     9742,
     13243
    ],
    [
     9658,
     13307
    ],
    [
     9644,
     13346
    ],
    [
     9596,
     13370
    ],
    [
     9533,
     13386
    ],
    [
     9509,
     13355
    ]
   ]
  },
  {
   "name": "Annotation 3",
   "vertices": [
    [
     3566,
     21484
    ],
    [
     3549,
     21413
    ],
    [
     3603,
     21339
    ],
    [
     3683,
     21300
    ],
    [
     3761,
     21261
    ],
    [
     3846,
     21239
    ],
    [
     3891,
     21248
    ],
    [
     3982,
     21309
    ],
    [
     3963,
     21395
    ],
    [
     3915,
     21469
    ],
    [
     3857,
     21538
    ],
    [
     3772,
     21567
    ],
    [
     3685,
     21569
    ],
    [
     3592,
     21580
    ],
    [
     3540,
     21577
    ]
   ]
  },
  {
   "name": "Annotation 4",
   "vertices": [
    [
     5973,
     19451
    ],
    [
     6012,
     19362
    ],
    [
     5997,
     19243
    ],
    [
     5994,
     19171
    ],
    [
     6072,
     19214
    ],
    [
     6146,
     19271
    ],
    [
     6211,
     19336
    ],
    [
     6302,
     19397
    ],
    [
     6231,
     19459
    ],
    [
     6148,
     19501
    ],
    [
     6066,
     19535
    ],
    [
     6014,
     19537
    ]
   ]
  },
  {
   "name": "Annotation 5",
   "vertices": [
    [
     6805,
     19496
    ],
    [
     6721,
     19477
    ],
    [
     6781,
     19405
    ],
    [
     6868,
     19403
    ],
    [
     6957,
     19412
    ],
    [
     6994,
     19425
    ],
    [
     6950,
     19503
    ],
    [
     6931,
     19587
    ],
    [
     6927,
     19657
    ],
    [
     6864,
     19620
    ],
    [
     6809,
     19581
    ]
   ]
  },
  {
   "name": "Annotation 6",
   "vertices": [
    [
     7181,
     17743
    ],
    [
     7301,
     17731
    ],
    [
     7385,
     17696
    ],
    [
     7436,
     17659
    ],
    [
     7460,
     17659
    ],
    [
     7503,
     17713
    ],
    [
     7592,
     17700
    ],
    [
     7691,
     17684
    ],
    [
     7707,
     17686
    ],
    [
     7724,
     17750
    ],
    [
     7740,
     17812
    ],
    [
     7745,
     17879
    ],
    [
     7724,
     17941
    ],
    [
     7697,
     18001
    ],
    [
     7656,
     18051
    ],
    [
     7613,
     18100
    ],
    [
     7567,
     18144
    ],
    [
     7539,
     18151
    ],
    [
     7493,
     18093
    ],
    [
     7457,
     18038
    ],
    [
     7423,
     17977
    ],
    [
     7471,
     17934
    ],
    [
     7465,
     17903
    ],
    [
     7426,
     17877
    ],
    [
     7368,
     17844
    ],
    [
     7301,
     17832
    ],
    [
     7239,
     17818
    ],
    [
     7175,
     17794
    ],
    [
     7135,
     17759
    ]
   ]
  },
  {
   "name": "Annotation 7",
   "vertices": [
    [
     9742,
     13943
    ],
    [
     9801,
     13928
    ],
    [
     9765,
     13910
    ],
    [
     9666,
     13841
    ],
    [
     9641,
     13758
    ],
    [
     9645,
     13662
    ],
    [
     9624,
     13666
    ],
    [
     9584,
     13635
    ],
    [
     9586,
     13511
    ],
    [
     9616,
     13494
    ],
    [
     9672,
     13556
    ],
    [
     9724,
     13617
    ],
    [
     9786,
     13667
    ],
    [
     9842,
     13723
    ],
    [
     9880,
     13793
    ],
    [
     9944,
     13841
    ],
    [
     10004,
     13906
    ],
    [
     10000,
     13985
    ],
    [
     9978,
     14062
    ],
    [
     9969,
     14139
    ],
    [
     9900,
     14174
    ],
    [
     9842,
     14157
    ],
    [
     9840,
     14101
    ],
    [
     9822,
     14035
    ],
    [
     9747,
     13995
    ]
   ]
  },
  {
   "name": "Annotation 8",
   "vertices": [
    [
     10990,
     10816
    ],
    [
     10990,
     10680
    ],
    [
     10986,
     10533
    ],
    [
     11009,
     10464
    ],
    [
     11024,
     10387
    ],
    [
     11036,
     10360
    ],
    [
     11115,
     10368
    ],
    [
     11155,
     10364
    ],
    [
     11119,
     10244
    ],
    [
     11159,
     10221
    ],
    [
     11225,
     10273
    ],
    [
     11275,
     10335
    ],
    [
     11288,
     10344
    ],
    [
     11285,
     10423
    ],
    [
     11285,
     10502
    ],
    [
     11285,
     10581
    ],
    [
     11285,
     10662
    ],
    [
     11281,
     10739
    ],
    [
     11256,
     10763
    ],
    [
     11179,
     10803
    ],
    [
     11103,
     10841
    ],
    [
     11040,
     10861
    ],
    [
     11121,
     10870
    ],
    [
     11192,
     10903
    ],
    [
     11213,
     10922
    ],
    [
     11132,
     10955
    ],
    [
     11051,
     10942
    ],
    [
     10974,
     10920
    ],
    [
     10901,
     10880
    ],
    [
     10924,
     10824
    ],
    [
     10963,
     10813
    ]
   ]
  },
  {
   "name": "Annotation 9",
   "vertices": [
    [
     11120,
     7114
    ],
    [
     11058,
     7022
    ],
    [
     11070,
     6906
    ],
    [
     11107,
     6810
    ],
    [
     11171,
     6729
    ],
    [
     11255,
     6669
    ],
    [
     11310,
     6684
    ],
    [
     11337,
     6780
    ],
    [
     11391,
     6872
    ],
    [
     11401,
     6770
    ],
    [
     11403,
     6667
    ],
    [
     11423,
     6566
    ],
    [
     11502,
     6462
    ],
    [
     11584,
     6521
    ],
    [
     11606,
     6620
    ],
    [
     11606,
     6729
    ],
    [
     11579,
     6825
    ],
    [
     11537,
     6924
    ],
    [
     11500,
     7017
    ],
    [
     11475,
     7114
    ],
    [
     11460,
     7215
    ],
    [
     11453,
     7237
    ],
    [
     11497,
     7146
    ],
    [
     11579,
     7062
    ],
    [
     11603,
     7163
    ],
    [
     11574,
     7267
    ],
    [
     11547,
     7363
    ],
    [
     11522,
     7437
    ],
    [
     11448,
     7370
    ],
    [
     11359,
     7318
    ],
    [
     11332,
     7306
    ],
    [
     11265,
     7380
    ],
    [
     11241,
     7476
    ],
    [
     11206,
     7521
    ],
    [
     11174,
     7422
    ],
    [
     11211,
     7328
    ],
    [
     11221,
     7227
    ],
    [
     11176,
     7136
    ]
   ]
  }
 ],
 "negative": []
}