{
 "positive": [
  {
   "name": "Annotation 0",
   "vertices": [
    [
     19974,
     27439
    ],
    [
     19669,
     26828
    ],
    [
     19822,
     25605
    ],
    [
     20433,
     24102
    ],
    [
     20815,
     23210
    ],
    [
     21325,
     22675
    ],
    [
     21987,
     22446
    ],
    [
     22446,
     21911
    ],
    [
     23006,
     21427
    ],
    [
     23363,
     21707
    ],
    [
     24790,
     23516
    ],
    [
     25452,
     23949
    ],
    [
     25580,
     23643
    ],
    [
     25146,
     22930
    ],
    [
     24051,
     22369
    ],
    [
     23745,
     21299
    ],
    [
     24229,
     20459
    ],
    [
     25860,
     20306
    ],
    [
     27796,
     21019
    ],
    [
     28382,
     21554
    ],
    [
     28637,
     22981
    ],
    [
     28739,
     23694
    ],
    [
     28739,
     23847
    ],
    [
     27796,
     23439
    ],
    [
     27363,
     22726
    ],
    [
     26879,
     22344
    ],
    [
     26777,
     23185
    ],
    [
     27338,
     23898
    ],
    [
     27847,
     24051
    ],
    [
     28433,
     24178
    ],
    [
     29172,
     24535
    ],
    [
     28586,
     25223
    ],
    [
     28866,
     25248
    ],
    [
     29681,
     24764
    ],
    [
     29962,
     24637
    ],
    [
     30420,
     25019
    ],
    [
     30777,
     25452
    ],
    [
     30675,
     26115
    ],
    [
     30879,
     26981
    ],
    [
     31134,
     27338
    ],
    [
     32178,
     27490
    ],
    [
     32025,
     27032
    ],
    [
     31924,
     26267
    ],
    [
     33070,
     26675
    ],
    [
     33681,
     27414
    ],
    [
     34369,
     28076
    ],
    [
     34981,
     28815
    ],
    [
     36127,
     29631
    ],
    [
     36892,
     30318
    ],
    [
     37045,
     30548
    ],
    [
     37019,
     30853
    ],
    [
     36739,
     31338
    ],
    [
     36713,
     32102
    ],
    [
     36637,
     33070
    ],
    [
     36280,
     34318
    ],
    [
     35694,
     34650
    ],
    [
     35847,
     35185
    ],
    [
     35898,
     35643
    ],
    [
     35414,
     37325
    ],
    [
     34369,
     37885
    ],
    [
     32611,
     36459
    ],
    [
     31618,
     35771
    ],
    [
     30344,
     33885
    ],
    [
     30471,
     32076
    ],
    [
     30548,
     30726
    ],
    [
     30802,
     29911
    ],
    [
     29885,
     31006
    ],
    [
     29834,
     31873
    ],
    [
     29885,
     32611
    ],
    [
     30038,
     33860
    ],
    [
     30802,
     35388
    ],
    [
     31287,
     35847
    ],
    [
     32662,
     37019
    ],
    [
     34318,
     38573
    ],
    [
     34038,
     39210
    ],
    [
     32637,
     39363
    ],
    [
     30981,
     38548
    ],
    [
     30344,
     37783
    ],
    [
     30089,
     38420
    ],
    [
     29299,
     38573
    ],
    [
     26828,
     37529
    ],
    [
     25529,
     36204
    ],
    [
     23847,
     34930
    ],
    [
     24025,
     34599
    ],
    [
     25274,
     34573
    ],
    [
     25452,
     34344
    ],
    [
     24790,
     34242
    ],
    [
     23414,
     33299
    ],
    [
     23185,
     33070
    ],
    [
     22981,
     33580
    ],
    [
     22675,
     33834
    ],
    [
     21503,
     33172
    ],
    [
     22038,
     32535
    ],
    [
     21962,
     31924
    ],
    [
     21503,
     30853
    ],
    [
     21376,
     29681
    ],
    [
     21580,
     29045
    ],
    [
     23822,
     27669
    ],
    [
     24178,
     26930
    ],
    [
     23414,
     27236
    ],
    [
     21681,
     28204
    ],
    [
     21503,
     28510
    ],
    [
     21248,
     29045
    ],
    [
     21121,
     29197
    ],
    [
     20637,
     28866
    ],
    [
     20076,
     28229
    ]
   ]
  },
  {
   "name": "Annotation 1",
   "vertices": [
    [
     26466,
     8200
    ],
    [
     26544,
     7985
    ],
    [
     26639,
     7856
    ],
    [
     26527,
     7580
    ],
    [
     26501,
     7408
    ],
    [
     26372,
     7245
    ],
    [
     26492,
     6987
    ],
    [
     26759,
     6720
    ],
    [
     26879,
     6591
    ],
    [
     26639,
     6445
    ],
    [
     26699,
     6135
    ],
    [
     27043,
     5945
    ],
    [
     27267,
     5954
    ],
    [
     27542,
     6066
    ],
    [
     27903,
     6143
    ],
    [
     28239,
     6264
    ],
    [
     28420,
     6384
    ],
    [
     28497,
     6505
    ],
    [
     28402,
     6582
    ],
    [
     28179,
     6651
    ],
    [
     27757,
     6746
    ],
    [
     27499,
     6832
    ],
    [
     27714,
     6961
    ],
    [
     27938,
     7098
    ],
    [
     28067,
     7271
    ],
    [
     28506,
     7262
    ],
    [
     28729,
     7184
    ],
    [
     28910,
     7288
    ],
    [
     28919,
     7503
    ],
    [
     28652,
     7864
    ],
    [
     28566,
     8002
    ],
    [
     28540,
     8097
    ],
    [
     28592,
     8406
    ],
    [
     28256,
     8527
    ],
    [
     27964,
     8501
    ],
    [
     27835,
     8570
    ],
    [
     27774,
     8750
    ],
    [
     27628,
     8931
    ],
    [
     27396,
     8802
    ],
    [
     27292,
     8596
    ],
    [
     27206,
     8535
    ],
    [
     27060,
     8793
    ],
    [
     27052,
     8923
    ],
    [
     26897,
     9069
    ],
    [
     26604,
     9060
    ],
    [
     26458,
     8948
    ],
    [
     26208,
     8974
    ],
    [
     26062,
     8828
    ],
    [
     25830,
     8742
    ],
    [
     25985,
     8664
    ],
    [
     26053,
     8484
    ],
    [
     26140,
     8380
    ],
    [
     26423,
     8312
    ]
   ]
  }
 ],
 "negative": []
}